README.md
setup.py
pytest_jar_yuan/RerunVerifyFail.py
pytest_jar_yuan/__init__.py
pytest_jar_yuan/all.py
pytest_jar_yuan/ctrl_pg.py
pytest_jar_yuan/ctrl_run.py
pytest_jar_yuan/gen_opt_rslt.py
pytest_jar_yuan/gen_vfy_tab.py
pytest_jar_yuan/handle_api.py
pytest_jar_yuan.egg-info/PKG-INFO
pytest_jar_yuan.egg-info/SOURCES.txt
pytest_jar_yuan.egg-info/dependency_links.txt
pytest_jar_yuan.egg-info/top_level.txt